pypkg_setuptools_example-1.0.0.dist-info/top_level.txt
pypkg_setuptools_example-1.0.0.dist-info/WHEEL
pypkg_setuptools_example-1.0.0.dist-info/DESCRIPTION.rst
pypkg_setuptools_example-1.0.0.dist-info/METADATA
pypkg_setuptools_example-1.0.0.dist-info/RECORD
pypkg_setuptools_example-1.0.0.dist-info/metadata.json
main/__init__.py
main/main.py
