Metadata-Version: 2.0
Name: pypkg-setuptools-example
Version: 1.0.0
Summary: Example Python package for distribution via setuptools
Home-page: UNKNOWN
Author: Dennis Smiley
Author-email: aircastle.tech@gmail.com
License: MIT
Keywords: sample setuptools
Platform: UNKNOWN
Classifier: Programming Language :: Python :: 3.4
